produtils/__init__.py
produtils-0.3.0.dist-info/LICENSE.md
produtils-0.3.0.dist-info/METADATA
produtils-0.3.0.dist-info/WHEEL
produtils-0.3.0.dist-info/top_level.txt
produtils-0.3.0.dist-info/RECORD
