Metadata-Version: 2.1
Name: produtils
Version: 0.3.0
Summary: A nifty library of python productivity tools
Home-page: https://github.com/mukundraj/produtils
Author: Mukund Raj
Author-email: mukundraj2@gmail.com
License: UNKNOWN
Project-URL: Bug Tracker, https://github.com/mukundraj/produtils/issues
Platform: UNKNOWN
Classifier: Programming Language :: Python :: 3
Classifier: License :: OSI Approved :: MIT License
Classifier: Operating System :: OS Independent
Requires-Python: >=3.6
License-File: LICENSE.md
